pretix_advanced_stats/__init__.py
pretix_advanced_stats/apps.py
pretix_advanced_stats/signals.py
pretix_advanced_stats/urls.py
pretix_advanced_stats/views.py
pretix_advanced_stats/locale/de/LC_MESSAGES/django.mo
pretix_advanced_stats/locale/de/LC_MESSAGES/django.po
pretix_advanced_stats/locale/de_Informal/.gitkeep
pretix_advanced_stats/locale/de_Informal/LC_MESSAGES/django.mo
pretix_advanced_stats/locale/de_Informal/LC_MESSAGES/django.po
pretix_advanced_stats/static/pretix_advanced_stats/.gitkeep
pretix_advanced_stats/static/pretix_advanced_stats/chart.js
pretix_advanced_stats/static/pretix_advanced_stats/stats.js
pretix_advanced_stats/templates/pretix_advanced_stats/.gitkeep
pretix_advanced_stats/templates/pretix_advanced_stats/advanced_stats.html
pretix_plugin_advanced_stats-1.0.0.dist-info/LICENSE
pretix_plugin_advanced_stats-1.0.0.dist-info/METADATA
pretix_plugin_advanced_stats-1.0.0.dist-info/WHEEL
pretix_plugin_advanced_stats-1.0.0.dist-info/entry_points.txt
pretix_plugin_advanced_stats-1.0.0.dist-info/top_level.txt
pretix_plugin_advanced_stats-1.0.0.dist-info/RECORD
