Metadata-Version: 2.2
Name: pretix-plugin-advanced-stats
Version: 1.0.0
Summary: Short description
Author: Ernesto Arbitrio
Author-email: pamaron <ernesto.arbitrio@gmail.com>
Maintainer-email: pamaron <ernesto.arbitrio@gmail.com>
License: Apache
Keywords: pretix
License-File: LICENSE
Dynamic: author
